jiradls/__init__.py
jiradls/command_line.py
jiradls/diamond.py
jiradls/dlsjira.py
jiradls/workflow.py
jiradls-1.0.dist-info/LICENSE
jiradls-1.0.dist-info/METADATA
jiradls-1.0.dist-info/WHEEL
jiradls-1.0.dist-info/entry_points.txt
jiradls-1.0.dist-info/top_level.txt
jiradls-1.0.dist-info/RECORD
