Metadata-Version: 2.1
Name: jiradls
Version: 1.0
Summary: A JIRA command line interface for the DLS instance
Home-page: https://github.com/DiamondLightSource/python-jira
Author: Markus Gerstel
Author-email: scientificsoftware@diamond.ac.uk
License: BSD
Download-URL: https://github.com/DiamondLightSource/python-jira/releases
Platform: UNKNOWN
Classifier: Development Status :: 5 - Production/Stable
Classifier: License :: OSI Approved :: BSD License
Classifier: Programming Language :: Python :: 3
Classifier: Programming Language :: Python :: 3.6
Classifier: Programming Language :: Python :: 3.7
Classifier: Programming Language :: Python :: 3.8
Classifier: Programming Language :: Python :: 3.9
Classifier: Operating System :: OS Independent
Classifier: Topic :: Software Development :: Bug Tracking
Requires-Python: >=3.6
Requires-Dist: colorama
Requires-Dist: cryptography
Requires-Dist: jira
Requires-Dist: prompt-toolkit
Requires-Dist: pyjwt
